responseSpect/__init__.py
responseSpect/responseSpect.dll
responseSpect/responseSpectMain.py
responseSpect/responseSpectWrapper.py
responseSpect/responseTest.py
responseSpect-0.0.0.dist-info/METADATA
responseSpect-0.0.0.dist-info/WHEEL
responseSpect-0.0.0.dist-info/top_level.txt
responseSpect-0.0.0.dist-info/RECORD
