Metadata-Version: 2.1
Name: responseSpect
Version: 0.0.0
Summary: acceleration,velocity and displacement response spectra calculation
Home-page: https://github.com/Junjun1guo/responseSpect
Author: Junjun Guo
Author-email: guojj01@gmail.com
License: UNKNOWN
Keywords: response sepctra,accelearion,velocity,displacement
Platform: UNKNOWN
Classifier: Topic :: Software Development :: Build Tools
Classifier: License :: OSI Approved :: MIT License
Classifier: Programming Language :: Python :: 3
Classifier: Programming Language :: Python :: 3.6
Classifier: Programming Language :: Python :: 3.7
Classifier: Programming Language :: Python :: 3.8
Classifier: Programming Language :: Python :: 3 :: Only
Requires-Python: >=3.6
